finbull/__init__.py
finbull/error.py
finbull/__pycache__/__init__.cpython-37.pyc
finbull/__pycache__/error.cpython-37.pyc
finbull/driver/__init__.py
finbull/driver/gremlin_server.py
finbull/driver/__pycache__/__init__.cpython-37.pyc
finbull/driver/__pycache__/gremlin_server.cpython-37.pyc
finbull/finlib/__init__.py
finbull/finlib/andes.py
finbull/finlib/edb.py
finbull/finlib/__pycache__/__init__.cpython-37.pyc
finbull/finlib/__pycache__/andes.cpython-37.pyc
finbull/finlib/__pycache__/edb.cpython-37.pyc
finbull-1.0.8.dist-info/LICENSE
finbull-1.0.8.dist-info/METADATA
finbull-1.0.8.dist-info/WHEEL
finbull-1.0.8.dist-info/top_level.txt
finbull-1.0.8.dist-info/RECORD
