Metadata-Version: 2.1
Name: finbull
Version: 1.0.8
Summary: the finbull framework.
Home-page: https://code.aliyun.com/finsight/FinBull
Author: wangjiangfeng
Author-email: wangjiangfeng@hcyjs.com
License: The MIT LICENSE (MIT)
Platform: UNKNOWN
Classifier: Programming Language :: Python :: 3.7
Classifier: Programming Language :: Python :: Implementation :: CPython
Classifier: Programming Language :: Python :: Implementation :: PyPy
Requires-Dist: requests (>=2.22.0)
Requires-Dist: pandas (>=0.24.2)
Requires-Dist: numpy (>=1.15.4)
Requires-Dist: tornado (>=4.4.2)
Requires-Dist: tornadis (>=0.8.0)
Requires-Dist: configobj (>=5.0.6)
Requires-Dist: six (>=1.10.0)
Requires-Dist: neo4j (>=4.0.0)
Requires-Dist: oss2 (>=2.9.0)
Requires-Dist: pyyaml (>=5.1.2)
